policyuniverse/__init__.py
policyuniverse/action.py
policyuniverse/action_categories.py
policyuniverse/arn.py
policyuniverse/common.py
policyuniverse/data.json
policyuniverse/expander_minimizer.py
policyuniverse/organization.py
policyuniverse/policy.py
policyuniverse/statement.py
policyuniverse-1.5.1.20231109.dist-info/LICENSE
policyuniverse-1.5.1.20231109.dist-info/METADATA
policyuniverse-1.5.1.20231109.dist-info/WHEEL
policyuniverse-1.5.1.20231109.dist-info/top_level.txt
policyuniverse-1.5.1.20231109.dist-info/RECORD
