Metadata-Version: 2.1
Name: policyuniverse
Version: 1.5.1.20231109
Summary: Parse and Process AWS IAM Policies, Statements, ARNs, and wildcards.
Home-page: https://github.com/Netflix-Skunkworks/policyuniverse
Author: Patrick Kelley
Author-email: patrickbarrettkelley@gmail.com
Keywords: iam,arn,action_groups,condition,policy,statement,wildcard
Classifier: License :: OSI Approved :: Apache Software License
Requires-Python: >=3.7
License-File: LICENSE
Provides-Extra: tests
Requires-Dist: pytest; extra == "tests"
Requires-Dist: coveralls; extra == "tests"
Requires-Dist: bandit; extra == "tests"
Provides-Extra: dev
Requires-Dist: pre-commit; extra == "dev"
Requires-Dist: black; extra == "dev"
